culsans/__init__.py
culsans/_exceptions.py
culsans/_protocols.py
culsans/_proxies.py
culsans/_queues.py
culsans/_utils.py
culsans/py.typed
culsans-0.10.0.dist-info/METADATA
culsans-0.10.0.dist-info/WHEEL
culsans-0.10.0.dist-info/RECORD
