Metadata-Version: 2.4
Name: culsans
Version: 0.10.0
Summary: Thread-safe async-aware queue for Python
Project-URL: Homepage, https://github.com/x42005e1f/culsans
Project-URL: Documentation, https://culsans.readthedocs.io
Project-URL: Changelog, https://culsans.readthedocs.io/latest/changelog.html
Author-email: Ilya Egorov <0x42005e1f@gmail.com>
Keywords: anyio,async,async-await,asyncio,communication,concurrency,eventlet,gevent,greenlet,library,mypy,python,queue,thread-safety,threading,trio
Classifier: Development Status :: 3 - Alpha
Classifier: Framework :: AnyIO
Classifier: Framework :: AsyncIO
Classifier: Framework :: Trio
Classifier: Intended Audience :: Developers
Classifier: License :: OSI Approved :: ISC License (ISCL)
Classifier: Operating System :: OS Independent
Classifier: Programming Language :: Python :: 3 :: Only
Classifier: Programming Language :: Python :: 3.8
Classifier: Programming Language :: Python :: 3.9
Classifier: Programming Language :: Python :: 3.10
Classifier: Programming Language :: Python :: 3.11
Classifier: Programming Language :: Python :: 3.12
Classifier: Programming Language :: Python :: 3.13
Classifier: Programming Language :: Python :: 3.14
Classifier: Programming Language :: Python :: Free Threading :: 2 - Beta
Classifier: Programming Language :: Python :: Implementation :: CPython
Classifier: Programming Language :: Python :: Implementation :: PyPy
Classifier: Topic :: Software Development :: Libraries :: Python Modules
Classifier: Typing :: Typed
Requires-Python: >=3.8
Requires-Dist: aiologic>=0.13.0
Requires-Dist: typing-extensions>=4.5.0; python_version < '3.12'
